realcugan_ncnn_py-2.0.0.dist-info/METADATA
realcugan_ncnn_py-2.0.0.dist-info/WHEEL
realcugan_ncnn_py-2.0.0.dist-info/licenses/LICENSE
realcugan_ncnn_py/__init__.py
realcugan_ncnn_py/models/models-nose/up2x-no-denoise.bin
realcugan_ncnn_py/models/models-nose/up2x-no-denoise.param
realcugan_ncnn_py/models/models-pro/up2x-conservative.bin
realcugan_ncnn_py/models/models-pro/up2x-conservative.param
realcugan_ncnn_py/models/models-pro/up2x-denoise3x.bin
realcugan_ncnn_py/models/models-pro/up2x-denoise3x.param
realcugan_ncnn_py/models/models-pro/up2x-no-denoise.bin
realcugan_ncnn_py/models/models-pro/up2x-no-denoise.param
realcugan_ncnn_py/models/models-pro/up3x-conservative.bin
realcugan_ncnn_py/models/models-pro/up3x-conservative.param
realcugan_ncnn_py/models/models-pro/up3x-denoise3x.bin
realcugan_ncnn_py/models/models-pro/up3x-denoise3x.param
realcugan_ncnn_py/models/models-pro/up3x-no-denoise.bin
realcugan_ncnn_py/models/models-pro/up3x-no-denoise.param
realcugan_ncnn_py/models/models-se/up2x-conservative.bin
realcugan_ncnn_py/models/models-se/up2x-conservative.param
realcugan_ncnn_py/models/models-se/up2x-denoise1x.bin
realcugan_ncnn_py/models/models-se/up2x-denoise1x.param
realcugan_ncnn_py/models/models-se/up2x-denoise2x.bin
realcugan_ncnn_py/models/models-se/up2x-denoise2x.param
realcugan_ncnn_py/models/models-se/up2x-denoise3x.bin
realcugan_ncnn_py/models/models-se/up2x-denoise3x.param
realcugan_ncnn_py/models/models-se/up2x-no-denoise.bin
realcugan_ncnn_py/models/models-se/up2x-no-denoise.param
realcugan_ncnn_py/models/models-se/up3x-conservative.bin
realcugan_ncnn_py/models/models-se/up3x-conservative.param
realcugan_ncnn_py/models/models-se/up3x-denoise3x.bin
realcugan_ncnn_py/models/models-se/up3x-denoise3x.param
realcugan_ncnn_py/models/models-se/up3x-no-denoise.bin
realcugan_ncnn_py/models/models-se/up3x-no-denoise.param
realcugan_ncnn_py/models/models-se/up4x-conservative.bin
realcugan_ncnn_py/models/models-se/up4x-conservative.param
realcugan_ncnn_py/models/models-se/up4x-denoise3x.bin
realcugan_ncnn_py/models/models-se/up4x-denoise3x.param
realcugan_ncnn_py-2.0.0.dist-info/RECORD
