Metadata-Version: 2.1
Name: realcugan-ncnn-py
Version: 2.0.0
Author-Email: Tohrusky <65994850+Tohrusky@users.noreply.github.com>
License: BSD-3-Clause
Classifier: Programming Language :: Python :: 3.8
Classifier: Programming Language :: Python :: 3.9
Classifier: Programming Language :: Python :: 3.10
Classifier: Programming Language :: Python :: 3.11
Classifier: Programming Language :: Python :: 3.12
Classifier: Programming Language :: C++
Project-URL: Homepage, https://github.com/Final2x/realcugan-ncnn-py
Project-URL: Repository, https://github.com/Final2x/realcugan-ncnn-py
Requires-Python: >=3.8
Requires-Dist: opencv-python
Requires-Dist: pillow
